OldHangeul/__init__.py
OldHangeul/make_dic.py
OldHangeul/old_hangeul.py
OldHangeul/data/final_jamo.pickle
OldHangeul/data/initial_jamo.pickle
OldHangeul/data/ipf.pickle
OldHangeul/data/jamo_list.pickle
OldHangeul/data/jamo_list_all.pickle
OldHangeul/data/jamo_list_key.pickle
OldHangeul/data/medial_jamo.pickle
OldHangeul-1.2.0.dist-info/METADATA
OldHangeul-1.2.0.dist-info/WHEEL
OldHangeul-1.2.0.dist-info/top_level.txt
OldHangeul-1.2.0.dist-info/RECORD
