Metadata-Version: 2.1
Name: OldHangeul
Version: 1.2.0
Summary: Program with functions for manipulation of old Korean script, including Unicode normalization and jamo separation.
Home-page: https://github.com/go00ood/OldHangeul
Author: go00od
Author-email: go00od@naver.com
Requires-Python: >=3
